{
  "simple_history": [
    [
      "최근 12시간 기준으로 '태풍상사'에 대한 유튜브 댓글 반응을 요약해줘.",
      "## 태풍상사 유튜브 댓글 반응 요약 (최근 12시간)\n\n**전반적 반응:** 긍정적 반응이 압도적으로 많으며, 이준호 배우의 연기, 드라마의 재미, 캐릭터에 대한 호평이 주를 이룹니다.\n\n**핵심 포인트:**\n\n*   **이준호 연기 칭찬:** 강태풍 역을 맡은 이준호의 연기력에 대한 극찬이 쏟아집니다. 특히, 오열 연기, 능글맞은 연기, 귀여운 모습 등 다양한 면모를 긍정적으로 평가합니다.\n*   **드라마 재미:** 드라마 자체의 재미를 언급하며, 웃음과 감동을 동시에 느꼈다는 반응이 많습니다.\n*   **캐릭터 매력:** 강태풍 캐릭터의 매력에 푹 빠졌다는 반응이 많으며, 특히 '귀엽다', '사랑스럽다'는 표현이 자주 등장합니다.\n*   **공감대 형성:** 특정 장면이나 대사에 공감하며 자신의 경험과 연결 짓는 댓글도 보입니다.\n\n**대략적인 비율:**\n\n*   긍정: 90% 이상\n*   부정: 0%\n*   중립: 10% 미만 (의견 요청, 단순 이모티콘 등)\n\n**대표 코멘트:**\n\n1.  \"너무 재밌어요, 초보자인 척 이 부분을 연기하는 게 너무 귀여워요!\"\n2.  \"이준호가 연기하는 강태풍이 너무 사랑스럽다\"\n3.  \"이준호이기에 가능한 강태풍 😊 우는 연기 어쩜 저렇게 슬프게 잘 해 ㅠㅠ\"\n4.  \"아침부터 이 장면을 봐서 출근길에 오열하는 사람 됨...ㅠㅠ 이준호 연기 진짜... ㅠㅠㅠ\"\n5.  \"ㅋㅋㅋㅋㅋ \" 아 저 3번이그등여~\" 이 말투 나의 ㅇㅇ 말투랑 넘나 똑같다 ㅋㅋㅋ 정말 이준호 너무 귀엽다~~ 사람이 도대체 매력이 몇개인지 셀 수가 없네😍\"\n6.  \"무덤덤하게 미선이가 전하는 아버지의 마지막 말을 듣고 저때까지도 아버지에 대한 그리움 슬픔을 자각하지 못하다가 통장에 남긴 메세지를 보고 갑자기 터져나오는 울음을 보고 같이 울어버림ㅠ\"\n7.  \"가슴찡한 명장명 중 하나 강태풍 오열연기💛💛💛\"\n8.  \"근데 오열하는 와중에 남모가 청진기 챙거준거 생각나서 또 웃김 ㅋㅋ\"\n9.  \"친구 케미 너무 좋다구 😍😍😍\"\n10. \"넘잼있어요 ㅋㅋㅋ ❤❤❤\"\n"
    ]
  ],
  "adv_history": [],
  "simple_query": "태풍상사",
  "last_keyword": "",
  "preset": "최근 12시간",
  "saved_at_kst": "2025-10-14 09:08:46"
}